wakawaka/__init__.py
wakawaka/admin.py
wakawaka/forms.py
wakawaka/locale/da/LC_MESSAGES/django.mo
wakawaka/locale/da/LC_MESSAGES/django.po
wakawaka/locale/de/LC_MESSAGES/django.mo
wakawaka/locale/de/LC_MESSAGES/django.po
wakawaka/locale/en/LC_MESSAGES/django.mo
wakawaka/locale/en/LC_MESSAGES/django.po
wakawaka/migrations/0001_initial.py
wakawaka/migrations/0002_auto_20160409_0645.py
wakawaka/migrations/0003_alter_revision_options_alter_wikipage_options_and_more.py
wakawaka/migrations/__init__.py
wakawaka/models.py
wakawaka/templates/wakawaka/base.html
wakawaka/templates/wakawaka/changes.html
wakawaka/templates/wakawaka/edit.html
wakawaka/templates/wakawaka/page.html
wakawaka/templates/wakawaka/page_list.html
wakawaka/templates/wakawaka/revision_list.html
wakawaka/templates/wakawaka/revision_table.html
wakawaka/templates/wakawaka/revisions.html
wakawaka/templatetags/__init__.py
wakawaka/templatetags/wakawaka_tags.py
wakawaka/tests/__init__.py
wakawaka/tests/base.py
wakawaka/tests/test_changes.py
wakawaka/tests/test_index.py
wakawaka/tests/test_page.py
wakawaka/tests/test_page_list.py
wakawaka/tests/test_project/__init__.py
wakawaka/tests/test_project/settings.py
wakawaka/tests/test_project/templates/404.html
wakawaka/tests/test_project/templates/500.html
wakawaka/tests/test_project/templates/registration/logged_out.html
wakawaka/tests/test_project/templates/registration/login.html
wakawaka/tests/test_project/templates/wakawaka/base.html
wakawaka/tests/test_project/urls.py
wakawaka/tests/test_project/wsgi.py
wakawaka/tests/test_revisions.py
wakawaka/tests/test_templatetags.py
wakawaka/urls.py
wakawaka/views.py
django_wakawaka-1.6.dist-info/LICENSE
django_wakawaka-1.6.dist-info/METADATA
django_wakawaka-1.6.dist-info/WHEEL
django_wakawaka-1.6.dist-info/RECORD
